{"cameraMode":{"drawMode":0,"name":"Shaded","section":"Shading Mode"},"sceneLighting":false,"audioPlay":false,"sceneViewState":{"m_AlwaysRefresh":false,"showFog":false,"showSkybox":false,"showFlares":false,"showImageEffects":false,"showParticleSystems":false,"showVisualEffectGraphs":true,"m_FxEnabled":true},"in2DMode":false,"pivot":{"x":-9.920000076293946,"y":5.75,"z":-20.31999969482422},"rotation":{"x":-0.0560610331594944,"y":0.9437510967254639,"z":-0.22047565877437592,"w":-0.23997493088245393},"size":10.0,"orthographic":false}